README.txt
ez_setup.py
setup.py
whs.utils.pyman.egg-info/PKG-INFO
whs.utils.pyman.egg-info/SOURCES.txt
whs.utils.pyman.egg-info/dependency_links.txt
whs.utils.pyman.egg-info/namespace_packages.txt
whs.utils.pyman.egg-info/top_level.txt
whs/utils/__init__.py
whs/utils/pyman.py